lumeo/__init__.py
lumeo/utils.py
lumeo/api/__init__.py
lumeo/api/api.py
lumeo/api/lumeo_types.py
lumeo/pipeline/__init__.py
lumeo/pipeline/display/__init__.py
lumeo/pipeline/display/display.py
lumeo/pipeline/inference/__init__.py
lumeo/pipeline/inference/inference.py
lumeo/pipeline/metadata/__init__.py
lumeo/pipeline/metadata/metadata.py
lumeo/pipeline/utils/__init__.py
lumeo/pipeline/utils/extras.py
lumeo/pipeline/utils/log_events.py
lumeo/scripts/__init__.py
lumeo/scripts/avigilon/__init__.py
lumeo/scripts/avigilon/import_cameras.py
lumeo/scripts/bulk_delete/__init__.py
lumeo/scripts/bulk_delete/__main__.py
lumeo/scripts/bulk_delete/bulk_delete.py
lumeo/scripts/bulk_deploy/README.md
lumeo/scripts/bulk_deploy/__init__.py
lumeo/scripts/bulk_deploy/__main__.py
lumeo/scripts/bulk_deploy/bulk_deploy.py
lumeo/scripts/bulk_deploy/deployer.py
lumeo/scripts/custom_function/__init__.py
lumeo/scripts/custom_function/create_repo.py
lumeo/scripts/hanwhawave/__init__.py
lumeo/scripts/hanwhawave/import_cameras.py
lumeo/scripts/hikcentral/__init__.py
lumeo/scripts/hikcentral/import_cameras.py
lumeo/scripts/load_test/__init__.py
lumeo/scripts/load_test/__main__.py
lumeo/scripts/load_test/load_test.py
lumeo/scripts/media/__init__.py
lumeo/scripts/media/download.py
lumeo/scripts/model/__init__.py
lumeo/scripts/model/model_management.py
lumeo/scripts/rhombus/__init__.py
lumeo/scripts/rhombus/copy_footage.py
lumeo/scripts/rhombus/rhombus_logging.py
lumeo/scripts/rhombus/rhombus_mpd_info.py
lumeo/scripts/verkada/__init__.py
lumeo/scripts/verkada/import_cameras.py
lumeo-0.1.36.dist-info/LICENSE.txt
lumeo-0.1.36.dist-info/METADATA
lumeo-0.1.36.dist-info/WHEEL
lumeo-0.1.36.dist-info/entry_points.txt
lumeo-0.1.36.dist-info/top_level.txt
lumeo-0.1.36.dist-info/RECORD
