Metadata-Version: 2.1
Name: lumeo
Version: 0.1.36
Summary: Helper library for Lumeo video analytics platform
Home-page: https://github.com/lumeohq/lumeo-python/
Author: Lumeo
Author-email: support@lumeo.com
License: MIT
Project-URL: Documentation, https://docs.lumeo.com/
Platform: any
Classifier: Programming Language :: Python :: 3.8
Classifier: Programming Language :: Python :: 3.9
Classifier: Programming Language :: Python :: 3.10
Classifier: Programming Language :: Python :: 3.11
Classifier: Programming Language :: Python :: 3.12
Classifier: Development Status :: 4 - Beta
Classifier: License :: OSI Approved :: MIT License
Classifier: Operating System :: OS Independent
Requires-Python: >=3.8
License-File: LICENSE.txt
Provides-Extra: all
Requires-Dist: httpx >=0.27 ; extra == 'all'
Requires-Dist: backoff >=2.2 ; extra == 'all'
Requires-Dist: aiocache >=0.12 ; extra == 'all'
Requires-Dist: aiofiles >=23.2 ; extra == 'all'
Requires-Dist: anyio >=4.3 ; extra == 'all'
Requires-Dist: asyncio >=3.4 ; extra == 'all'
Requires-Dist: requests >=2.31 ; extra == 'all'
Requires-Dist: pyyaml <7.0,>=6.0 ; extra == 'all'
Requires-Dist: boto3 >=1.34 ; extra == 'all'
Requires-Dist: rich <14.0.0,>=13.8.0 ; extra == 'all'
Requires-Dist: argparse >=1.4 ; extra == 'all'
Requires-Dist: colorlog >=6.8 ; extra == 'all'
Requires-Dist: packaging >=24.0 ; extra == 'all'
Requires-Dist: importlib-metadata ; (python_version < "3.8") and extra == 'all'
Provides-Extra: api
Requires-Dist: httpx >=0.27 ; extra == 'api'
Requires-Dist: backoff >=2.2 ; extra == 'api'
Requires-Dist: aiocache >=0.12 ; extra == 'api'
Requires-Dist: aiofiles >=23.2 ; extra == 'api'
Requires-Dist: anyio >=4.3 ; extra == 'api'
Requires-Dist: asyncio >=3.4 ; extra == 'api'
Requires-Dist: requests >=2.31 ; extra == 'api'
Requires-Dist: pyyaml <7.0,>=6.0 ; extra == 'api'
Requires-Dist: importlib-metadata ; (python_version < "3.8") and extra == 'api'
Provides-Extra: scripts
Requires-Dist: boto3 >=1.34 ; extra == 'scripts'
Requires-Dist: rich <14.0.0,>=13.8.0 ; extra == 'scripts'
Requires-Dist: argparse >=1.4 ; extra == 'scripts'
Requires-Dist: colorlog >=6.8 ; extra == 'scripts'
Requires-Dist: packaging >=24.0 ; extra == 'scripts'
Requires-Dist: httpx >=0.27 ; extra == 'scripts'
Requires-Dist: backoff >=2.2 ; extra == 'scripts'
Requires-Dist: aiocache >=0.12 ; extra == 'scripts'
Requires-Dist: aiofiles >=23.2 ; extra == 'scripts'
Requires-Dist: anyio >=4.3 ; extra == 'scripts'
Requires-Dist: asyncio >=3.4 ; extra == 'scripts'
Requires-Dist: requests >=2.31 ; extra == 'scripts'
Requires-Dist: pyyaml <7.0,>=6.0 ; extra == 'scripts'
Requires-Dist: importlib-metadata ; (python_version < "3.8") and extra == 'scripts'
Provides-Extra: testing
Requires-Dist: setuptools ; extra == 'testing'
Requires-Dist: pytest ; extra == 'testing'
Requires-Dist: pytest-cov ; extra == 'testing'
